setup.py
tigran_test4/__init__.py
tigran_test4.egg-info/PKG-INFO
tigran_test4.egg-info/SOURCES.txt
tigran_test4.egg-info/dependency_links.txt
tigran_test4.egg-info/requires.txt
tigran_test4.egg-info/top_level.txt